tap_planetscaleapi/__init__.py
tap_planetscaleapi/__main__.py
tap_planetscaleapi/client.py
tap_planetscaleapi/streams.py
tap_planetscaleapi/tap.py
tap_planetscaleapi-0.4.3.dist-info/METADATA
tap_planetscaleapi-0.4.3.dist-info/WHEEL
tap_planetscaleapi-0.4.3.dist-info/entry_points.txt
tap_planetscaleapi-0.4.3.dist-info/licenses/LICENSE
tap_planetscaleapi-0.4.3.dist-info/RECORD
