Metadata-Version: 2.4
Name: tap-planetscaleapi
Version: 0.4.3
Summary: Singer tap for PlanetScaleAPI, built with the Meltano Singer SDK.
Project-URL: Homepage, https://github.com/reservoir-data/tap-planetscalepi
Project-URL: Documentation, https://github.com/reservoir-data/tap-planetscalepi#
Project-URL: Issue Tracker, https://github.com/reservoir-data/tap-planetscalepi/issues
Project-URL: Repository, https://github.com/reservoir-data/tap-planetscalepi
Author-email: Edgar Ramírez-Mondragón <edgarrm358@gmail.com>
License-Expression: Apache-2.0
License-File: LICENSE
Keywords: ELT,PlanetScaleAPI
Classifier: Intended Audience :: Developers
Classifier: Operating System :: OS Independent
Classifier: Programming Language :: Python :: 3.10
Classifier: Programming Language :: Python :: 3.11
Classifier: Programming Language :: Python :: 3.12
Classifier: Programming Language :: Python :: 3.13
Classifier: Programming Language :: Python :: 3.14
Requires-Python: >=3.10
Requires-Dist: singer-sdk~=0.51.0
Requires-Dist: toolz~=1.1.0
Requires-Dist: typing-extensions>=4.14.1; python_full_version < '3.12'
Provides-Extra: s3
Requires-Dist: s3fs>=2025.5.0; extra == 's3'
